[
  {
    "latitude": 51.65014739999999,
    "longitude": 19.6105997,
    "northLat": 5167260,
    "southLat": 5162768,
    "eastLon": 1963305,
    "westLon": 1958814,
    "tax": 0,
    "id": 1,
    "lat": 5165014,
    "lng": 1961059
  },
  {
    "latitude": 62.10421799999999,
    "longitude": 9.2546574,
    "northLat": 6212667,
    "southLat": 6208176,
    "eastLon": 927711,
    "westLon": 923219,
    "tax": 0,
    "id": 2,
    "lat": 6210421,
    "lng": 925465
  },
  {
    "latitude": 49.4808882,
    "longitude": 8.1281917,
    "northLat": 4950334,
    "southLat": 4945843,
    "eastLon": 815064,
    "westLon": 810573,
    "tax": 0,
    "id": 3,
    "lat": 4948088,
    "lng": 812819
  },
  {
    "latitude": 17.6890684,
    "longitude": 98.97892209999999,
    "northLat": 1771152,
    "southLat": 1766661,
    "eastLon": 9900137,
    "westLon": 9895646,
    "tax": 0,
    "id": 4,
    "lat": 1768906,
    "lng": 9897892
  },
  {
    "latitude": 69.9038678,
    "longitude": 29.2965155,
    "northLat": 6992632,
    "southLat": 6988141,
    "eastLon": 2931897,
    "westLon": 2927405,
    "tax": 0,
    "id": 5,
    "lat": 6990386,
    "lng": 2929651
  },
  {
    "latitude": 52.5173538,
    "longitude": 13.3951083,
    "northLat": 5253981,
    "southLat": 5249489,
    "eastLon": 1341756,
    "westLon": 1337265,
    "tax": 0,
    "id": 6,
    "lat": 5251735,
    "lng": 1339510
  },
  {
    "latitude": 52.368834,
    "longitude": 4.8892019,
    "northLat": 5239129,
    "southLat": 5234637,
    "eastLon": 491165,
    "westLon": 486674,
    "tax": 0,
    "id": 7,
    "lat": 5236883,
    "lng": 488920
  },
  {
    "latitude": 41.4014565,
    "longitude": 2.1727238,
    "northLat": 4142391,
    "southLat": 4137899,
    "eastLon": 219518,
    "westLon": 215026,
    "tax": 0,
    "id": 8,
    "lat": 4140145,
    "lng": 217272
  },
  {
    "latitude": 48.8028832,
    "longitude": 2.1278559,
    "northLat": 4882534,
    "southLat": 4878042,
    "eastLon": 215031,
    "westLon": 210539,
    "tax": 0,
    "id": 9,
    "lat": 4880288,
    "lng": 212785
  },
  {
    "latitude": 41.0257788,
    "longitude": 28.9742018,
    "northLat": 4104823,
    "southLat": 4100332,
    "eastLon": 2899665,
    "westLon": 2895174,
    "tax": 0,
    "id": 10,
    "lat": 4102577,
    "lng": 2897420
  }
]